simpledeepcell/__init__.py
simpledeepcell/main.py
simpledeepcell-0.1.3.dist-info/License.txt
simpledeepcell-0.1.3.dist-info/METADATA
simpledeepcell-0.1.3.dist-info/WHEEL
simpledeepcell-0.1.3.dist-info/RECORD
