Metadata-Version: 2.1
Name: simpledeepcell
Version: 0.1.3
Summary: Mesmer only code from deepcell-tf and deepcell-toolbox. simplifies import
Home-page: https://github.com/BenCaiello/simpledeepcell
License: modified Apache 2.0
Author: Ben Caiello
Author-email: caiello@musc.edu
Requires-Python: >=3.9,<3.11
Classifier: License :: Other/Proprietary License
Classifier: Programming Language :: Python :: 3
Classifier: Programming Language :: Python :: 3.9
Classifier: Programming Language :: Python :: 3.10
Requires-Dist: numpy (>=1.16.6)
Requires-Dist: opencv-python-headless (>=4.9.0.80,<4.10.0.0)
Requires-Dist: scikit-image (>=0.19.3)
Requires-Dist: scipy (>=1.2.3,<2)
Requires-Dist: tensorflow (>=2.8.0,<2.9.0)
Requires-Dist: tensorflow-addons (>=0.16.1,<0.17.0)
Project-URL: Repository, https://github.com/BenCaiello/simpledeepcell
